racli/__init__.py
racli/logic.py
racli/racli.py
racli/ractf/__init__.py
racli/ractf/abc.py
racli/ractf/category.py
racli/ractf/challenge.py
racli/ractf/ctf.py
racli/ractf/errors.py
racli/ractf/file.py
racli/ractf/helpers/requests.py
racli/ractf/hint.py
racli/utils/files.py
racli/utils/log.py
racli-2.0.12.dist-info/entry_points.txt
racli-2.0.12.dist-info/WHEEL
racli-2.0.12.dist-info/METADATA
racli-2.0.12.dist-info/RECORD
