Metadata-Version: 2.1
Name: racli
Version: 2.0.12
Summary: A command-line program for interacting with RACTF.
License: MIT
Author: Ben Griffiths
Author-email: sendbenspam@yahoo.co.uk
Requires-Python: >=3.6,<4.0
Classifier: License :: OSI Approved :: MIT License
Classifier: Programming Language :: Python :: 3
Classifier: Programming Language :: Python :: 3.6
Classifier: Programming Language :: Python :: 3.7
Classifier: Programming Language :: Python :: 3.8
Requires-Dist: click (>=7.1.2,<8.0.0)
